{ "type": "FeatureCollection", "crs": { "type": "name", "properties": { "name": "urn:ogc:def:crs:OGC:1.3:CRS84" } }, "features": [ 
{ "type": "Feature", "properties": { "Name": "William Falk-Wallace", "Description": "Sun Sep 29 01:15:20 EDT 2013; Location Accuracy: 65.000000" }, "geometry": { "type": "Point", "coordinates": [ -73.969698, 40.800896, 0.0 ] } },
{ "type": "Feature", "properties": { "Name": "William Falk-Wallace", "Description": "Sun Sep 29 00:48:56 EDT 2013; Location Accuracy: 65.000000" }, "geometry": { "type": "Point", "coordinates": [ -73.969704, 40.800879, 0.0 ] } },
{ "type": "Feature", "properties": { "Name": "William Falk-Wallace", "Description": "Sun Sep 29 00:41:53 EDT 2013; Location Accuracy: 65.000000" }, "geometry": { "type": "Point", "coordinates": [ -73.969704, 40.800879, 0.0 ] } },
{ "type": "Feature", "properties": { "Name": "William Falk-Wallace", "Description": "Sun Sep 29 00:34:34 EDT 2013; Location Accuracy: 65.000000" }, "geometry": { "type": "Point", "coordinates": [ -73.969707, 40.800858, 0.0 ] } },
{ "type": "Feature", "properties": { "Name": "William Falk-Wallace", "Description": "Sat Sep 28 23:14:45 EDT 2013; Location Accuracy: 65.000000" }, "geometry": { "type": "Point", "coordinates": [ -73.969681, 40.800861, 0.0 ] } },
{ "type": "Feature", "properties": { "Name": "William Falk-Wallace", "Description": "Sat Sep 28 23:12:17 EDT 2013; Location Accuracy: 65.000000" }, "geometry": { "type": "Point", "coordinates": [ -73.969649, 40.800850, 0.0 ] } },
{ "type": "Feature", "properties": { "Name": "William Falk-Wallace", "Description": "Thu Sep 26 12:17:11 EDT 2013; Location Accuracy: 65.000000" }, "geometry": { "type": "Point", "coordinates": [ -73.969623, 40.800795, 0.0 ] } }
]}
