{ "type": "FeatureCollection", "crs": { "type": "name", "properties": { "name": "urn:ogc:def:crs:OGC:1.3:CRS84" } }, "features": [ 
{ "type": "Feature", "properties": { "Name": "William Falk-Wallace", "Description": "Thu Sep 26 12:17:11 EDT 2013; Location Accuracy: 65.000000" }, "geometry": { "type": "Point", "coordinates": [ -73.969623, 40.800795, 0.0 ] } }
]}
